第3次验收/实验3/experiment3.v
module test3(A, B, En, Z);

input A, B, En;
output [3:0] Z;

assign Z[0] = ~(~(A) & ~(B) & En);
assign Z[1] = ~(~(A) & B & En);
assign Z[2] = ~(A & ~(B) & En);
assign Z[3] = ~(A & B & En);

endmodule

第3次验收/实验3/texperiment3.v
`include "experiment3.v"

//~ `New testbench
`timescale  1ns / 1ps

module tb_test3;

// test3 Inputs
reg   A                                    = 0 ;
reg   B                                    = 0 ;
reg   En                                   = 0 ;

// test3 Outputs
wire  [3:0]  Z                             ;

test3  u_test3 (
    .A                       ( A         ),
    .B                       ( B         ),
    .En                      ( En        ),

    .Z                       ( Z   [3:0] )
);

/*iverilog */
initial
begin
    $dumpfile("experiment3_wave.vcd");        //生成的vcd文件名称 注意脚本中生成的波形文件要名称相同
    $dumpvars(0, tb_test3);     //tb模块名称
end
/*iverilog */

initial
begin
    #10 A = 1'b0; B = 1'b1;
    #10 A = 1'b1; B = 1'b0;
    #10 A = 1'b1; B = 1'b1;
    #10 En = 1'b1; A = 1'b0; B = 1'b0;
    #10 A = 1'b0; B = 1'b1;
    #10 A = 1'b1; B = 1'b0;
    #10 A = 1'b1; B = 1'b1;

    #10 $finish;
end

endmodule

第3次验收/实验3/experiment3_wave.vcd
$date
	Thu Apr 27 15:40:11 2023
$end
$version
	Icarus Verilog
$end
$timescale
	1ps
$end
$scope module tb_test3 $end
$var wire 4 ! Z [3:0] $end
$var reg 1 " A $end
$var reg 1 # B $end
$var reg 1 $ En $end
$scope module u_test3 $end
$var wire 1 " A $end
$var wire 1 # B $end
$var wire 1 $ En $end
$var wire 4 % Z [3:0] $end
$upscope $end
$upscope $end
$enddefinitions $end
#0
$dumpvars
b1111 %
0$
0#
0"
b1111 !
$end
#10000
1#
#20000
0#
1"
#30000
1#
#40000
b1110 !
b1110 %
0#
0"
1$
#50000
b1101 !
b1101 %
1#
#60000
b1011 !
b1011 %
0#
1"
#70000
b111 !
b111 %
1#
