第4次验收/实验10/fsm_112.v
//给出的这个代码在检测到一次0111序列后就会失灵 不太完善 有机会要修改一下
module fsm_112(clk, in, out);

input clk, in;
output out;
reg[1:0] state;
parameter s0 = 2'b00, 
s1 = 2'b01, 
s2 = 2'b10, 
s3 = 2'b11;

assign out = (state == s3);
initial state = s0;
always @(posedge clk) 
begin
    if (in == 0) state <= s0;
    else state <= state + 1;
end

endmodule

第4次验收/实验10/testbench.v
`include"fsm_112.v"

//~ `New testbench
`timescale  1ns / 1ps

module tb_fsm_112;

// fsm_112 Parameters
parameter PERIOD = 10   ;

// fsm_112 Inputs
reg   clk                                  = 0 ;
reg   in                                   = 0 ;

// fsm_112 Outputs
wire  out                                  ;


initial
begin
    forever #(PERIOD/2)  clk=~clk;
end

fsm_112 u_fsm_112 (
    .clk                     ( clk   ),
    .in                      ( in    ),

    .out                     ( out   )
);

initial
begin
    $dumpfile("fsm_112.wave.vcd");
    $dumpvars(0, tb_fsm_112);
end

initial
begin
    #10; in = 1;

    #100;

    $finish;
end

endmodule

第4次验收/实验10/fsm_112.wave.vcd
$date
	Mon May 22 15:45:12 2023
$end
$version
	Icarus Verilog
$end
$timescale
	1ps
$end
$scope module tb_fsm_112 $end
$var wire 1 ! out $end
$var reg 1 " clk $end
$var reg 1 # in $end
$scope module u_fsm_112 $end
$var wire 1 " clk $end
$var wire 1 # in $end
$var wire 1 ! out $end
$var reg 2 $ state [1:0] $end
$upscope $end
$upscope $end
$enddefinitions $end
#0
$dumpvars
b0 $
0#
0"
0!
$end
#5000
1"
#10000
0"
1#
#15000
b1 $
1"
#20000
0"
#25000
b10 $
1"
#30000
0"
#35000
1!
b11 $
1"
#40000
0"
#45000
0!
b0 $
1"
#50000
0"
#55000
b1 $
1"
#60000
0"
#65000
b10 $
1"
#70000
0"
#75000
1!
b11 $
1"
#80000
0"
#85000
0!
b0 $
1"
#90000
0"
#95000
b1 $
1"
#100000
0"
#105000
b10 $
1"
