36单周期/mux.v
module mux2(a, b, s, y);

input s;             //选择信号
input[31:0] a,b;     //两个数据输入
output reg[31:0] y;  //输出
    
always @(*)
begin
    y <= (s == 0) ? a : b;
end

endmodule

36单周期/dm.v
module dm_4k(op, addr, din, dout, clk, MemWr);

input[5:0]	op;
input[31:0]	addr;
input[31:0]	din;
input		clk;
input		MemWr;
output[31:0]	dout;

reg[7:0] dm[4095:0]; //采取以字节位单位存储数据才是最合理的

integer i;

always @(negedge clk)
begin
if(MemWr)
begin
    if(op == 6'b101000)   //sb
        dm[addr] <= din[7:0];
    else {dm[addr + 3], dm[addr + 2], dm[addr + 1], dm[addr]} <= din;
end
end

assign dout = {dm[addr + 3], dm[addr + 2], dm[addr + 1], dm[addr]};

endmodule

36单周期/ALU.v
module ALU(ALUctr, A, B, shamt, result, zero);

input[4:0] ALUctr;
input[31:0] A, B;
input[4:0] shamt;

output[31:0] result;
output zero;

reg[31:0] result;

assign zero = (result == 32'b0); //0标志位

always @(*)
begin
	case(ALUctr)
		5'b00000: result <= A + B;//addu
		5'b00001: result <= A - B;//subu
		5'b00010://slt
			//由于内置比较运算只能进行无符号比较运算 有符号比较需要另加判断
			begin
				if(A[31] ^ B[31]) //如果符号位不同 显然存在大小关系
					result <= (A[31] == 1) ? 1 : 0; //若A符号为负 则显然A < B
				else //如果符号位相同 可以用内置运算比较
					//是负数比较的结果与补码视为无符号比较的结果不冲突
					result <= (A < B) ? 1 : 0;
			end
		5'b00011: result <= A & B;//and
		5'b00100: result <= ~(A | B);//nor
		5'b00101: result <= A | B;//or
		5'b00110: result <= A ^ B;//xor
		5'b00111: result <= B << shamt;//sll 逻辑左移
		5'b01000: result <= B >> shamt;//srl 逻辑右移
		5'b01001: result <= (A < B) ? 1 : 0;//sltu 可直接使用内置运算
		//5'b01010:jalr
		//5'b01011:jr
		//以上两条指令在alu阶段没有运算操作 即使涉及运算操作也放在寄存器组中进行了
		5'b01100: result <= B << A;//sllv 逻辑左移 左移量由寄存器提供
		//以下两个操作中 signed函数用来对操作数进行符号扩位 >>>是算术右移运算符 这两个步骤都是为了保证算数右移的正确性
		5'b01101: result <= $signed(B) >>> shamt;//sra 算数右移
		5'b01110: result <= $signed(B) >>> A;//srav //算数右移 右移量由寄存器提供
		5'b01111: result <= B >> A;//srlv //逻辑右移 右移量由寄存器提供
		5'b10000: result <= A + B;//addiu sign extension 无符号立即数加法 符号扩展
		//slti操作中传入的B已经是经过符号扩展之后的了
		5'b10001://slti 立即数无符号比较 比较逻辑类似于前面的slt
			begin
				if(A[31] ^ B[31])
					result <= (A[31] == 1) ? 1 : 0;
				else
					result <= (A < B) ? 1 : 0;
			end
		5'b10010: result <= (A < B) ? 1 : 0;//sltiu 立即数无符号比较
		5'b10011: result <= A & B;//andi
		5'b10100: result <= A | B;//ori
		5'b10101: result <= A ^ B;//xori
	endcase
end

endmodule

36单周期/extender.v
module extender(imm16, Extop, Exout);

input[15:0]	imm16;
input[1:0]	Extop;
output[31:0] Exout;

reg[31:0]	Exout;

always @(*)
begin
	if(Extop == 2'b00) //0扩展
		Exout <= {16'b0, imm16};
	else if(Extop == 2'b01) //符号扩展
		Exout <= {{16{imm16[15]}}, imm16};
	else if(Extop == 2'b10) //用于lui指令的高位赋值 低位0扩展
		Exout <= {imm16, 16'b0};
end

endmodule

36单周期/RegFile.v
module RegFile(op, PC, rs, rt, rd, shamt, func, data, RegWr, RegDst, ra, rb, clk, reset);

input[5:0]	 op;
input[31:2]	PC;
input[4:0]	rs,rt,rd,shamt;
input[5:0]	func;
input[31:0]	data;
input		RegWr;
input		RegDst;
input 		clk;	
input		reset;
output[31:0]	ra,rb;

reg[31:0]	rgs[31:0];
integer		i;

always @(negedge clk or posedge reset)
begin
	if(reset) //复位 所有寄存器初始化为0
	begin
		for(i = 0; i < 32; i = i + 1)
			rgs[i] <= 32'b0;
	end

	if(RegWr)
	begin
		case(op)
			6'b100000: //lb 装载字节 作符号扩展 此处alure是计算出的内存取值地址 根据除4的余数关系确定装载的字节是4个字节中的哪一个字
				begin
					rgs[rt] <= {{24{data[7]}}, data[7:0]};
				end
			6'b100100: //lbu 装载字节 作0扩展 此处alure是计算出的内存取值地址 根据与4的倍数关系确定装载的字节是4个字节中的哪一个字
				begin
					rgs[rt] <= {{24'b0}, data[7:0]};
				end		
			6'b000011: rgs[31] <= {(PC+30'd1), 2'b00}; //jal 在跳转同时还要将PC + 4并赋值给31号寄存器
			6'b001111: rgs[rt] <= {rd, shamt, func, 16'b0}; //lui 将立即数载入高位 末尾进行0扩展 这里的{rd, shamt, func}实际上是拼凑出了I型指令中的imm
			default:
				begin
					//jalr指令无法通过op判断 所以在这里另加判断
					if(rt == 0 && rd == 5'b11111 && shamt == 0 && func == 6'b001001)
						rgs[31] <= {(PC + 30'd1),2'b00}; //jalr 在跳转同时还要将PC + 4并赋值给31号寄存器
					//这里的操作可以省掉一个mux
					else if(RegDst == 1)	rgs[rd] <= data;
					else if(RegDst == 0)	rgs[rt] <= data;
				end 
		endcase
	end
end

//1. 这里的操作是为了保证0号寄存器的值始终为0
//2. 当输入地址的值为0时 输出的值永远是0 而不是寄存器中的值
//3. 此处设计的是组合逻辑电路
assign ra = (rs != 0) ? rgs[rs] : 0;
assign rb = (rt != 0) ? rgs[rt] : 0;

endmodule

36单周期/im.v
module im_4k(addr, dout);

input[31:2]	addr; //这里只采用[11:2]位可以避免处理PC初始地址0000_3000和im中存储第一条指令的地址0000_0000不匹配的问题
output[31:0] dout;

reg[31:0] im[1023:0];

initial
begin
    $readmemh("code.txt", im);
end

assign	dout = im[addr]; //设计成了组合逻辑电路 而非时序

endmodule

36单周期/NPC.v
module NPC(PC, zero, branch, op, imm16, target, jump, NPC, busA, rs, rt, rd, shamt, func);

input[31:2] PC;
input zero, branch, jump;
input[5:0] op, func;
input[15:0] imm16;
input[25:0] target;
input[31:0] busA;
input[4:0]	rs, rt, rd, shamt;
output[31:2] NPC;

reg[31:2] NPC;
wire[31:2] B_NPC = {{14{imm16[15]}}, imm16[15:0]} + PC; //条件跳转 将立即数进行符号扩展后与PC相加
wire[31:2] J_NPC = {PC[31:28], target}; //无条件跳转 target和PC组合成跳转指令
wire[31:2] N_NPC = PC + 1; //不发生跳转时正常的下一条指令

initial
begin
	NPC = 0;
end

always @(*)
begin
//根据op的不同来执行不同的操作
case(op)
	6'b000100: NPC = (zero == 1 && branch == 1) ? B_NPC : N_NPC;//beq
	6'b000101: NPC = (zero == 0 && branch == 1) ? B_NPC : N_NPC;//bne
	6'b000001: 
	//注意这里的bgez和bltz都是有符号比较 可以通过符号位来判断与0的大小关系
		begin
			if(rt == 1 && branch == 1 && (busA == 0 || busA[31] == 0))//bgez
				NPC = B_NPC;
			else if(rt == 0 && branch == 1 && busA[31] == 1 && busA != 0)//bltz 此处还要保证busA不为0是要排除-0的情况
				NPC = B_NPC;
			else	
				NPC = N_NPC;
		end
	6'b000111: NPC = (branch == 1 && busA[31] == 0 && busA != 0) ? B_NPC : N_NPC;//bgtz
	6'b000110: NPC = (branch == 1 && (busA[31] == 1 || busA == 0)) ? B_NPC : N_NPC;//blez 
	6'b000010: NPC = (jump == 1) ? J_NPC : N_NPC;//j 
	6'b000011: NPC = (jump == 1) ? J_NPC : N_NPC;//jal 该指令额外的操作并不在NPC中进行
	6'b000000: 
		begin
			if(rt == 0 && imm16 == 16'b1111100000001001)	
				NPC = busA[31:2];//jalr 同理 额外操作不在NPC中进行
			else if(rt == 0 && imm16 == 16'b0000000000001000)	
				NPC = busA[31:2];//jr
			else	
				NPC = N_NPC; 
		end
	default: NPC = N_NPC;
endcase
end

endmodule

36单周期/PC.v
module PC(NPC, clk, reset, PC);

input[31:2] NPC;
input clk,reset;
output[31:2] PC;

reg[31:2] PC;

initial
begin
	PC = 0;
end

always @(negedge clk or posedge reset)
begin
	if(reset)
		PC <= 0; //reset高电平时发生异步复位
	else
		PC <= NPC; //若复位信号无效 则在时钟下降沿将NPC赋值给PC
end

endmodule

36单周期/datapath.v
`include"PC.v"
`include"NPC.v"
`include"im.v"
`include"RegFile.v"
`include"extender.v"
`include"mux.v"
`include"ALU.v"
`include"dm.v"

module datapath(RegDst, RegWr, ALUSrc, MemWr, MemtoReg, ExtOp, ALUctr, Branch, Jump, clk, reset, instruction);

input RegDst, RegWr, ALUSrc, MemWr, MemtoReg, Branch, clk, reset, Jump;
input[1:0] ExtOp;
input[4:0] ALUctr;
output[31:0] instruction;

wire[31:2]	PC;
wire[31:2]	NPC;
wire		zero;
wire[31:0]	alure;     //alu result
wire[31:0]	exout;
wire[31:0]	r1,r2;
wire[31:0]	data2;
wire[31:0]	wdata;
wire[31:0]	dout;

PC pc(NPC, clk, reset, PC);
NPC npc(PC, zero, Branch, instruction[31:26], instruction[15:0], instruction[25:0], Jump, NPC, r1, instruction[25:21], instruction[20:16], instruction[15:11], instruction[10:6], instruction[5:0]);
im_4k ReOrM(PC, instruction);
RegFile RM(instruction[31:26], PC, instruction[25:21], instruction[20:16], instruction[15:11], instruction[10:6], instruction[5:0], wdata, RegWr, RegDst, r1, r2, clk, reset);
extender extM(instruction[15:0], ExtOp, exout);
mux2 mux2_32M(r2, exout, ALUSrc, data2);
ALU AM(ALUctr, r1, data2, instruction[10:6], alure, zero);
dm_4k DMM(instruction[31:26], alure, r2, dout, clk, MemWr);
mux2 mux2_M(alure, dout, MemtoReg, wdata);
	
endmodule

36单周期/ctrl.v
module ctrl(op, func, RegDst, RegWr, ALUSrc, MemWr, MemtoReg, ExtOp, ALUctr, Branch, Jump);

input[5:0] 	op;
input[5:0]	func;
output		RegDst;
output		RegWr;
output		ALUSrc;
output		MemWr;
output		MemtoReg;
output[1:0]	ExtOp;
output[4:0]	ALUctr;
output		Branch;
output		Jump;		

reg[13:0]	controls;

assign {RegDst, RegWr, ALUSrc, MemWr, MemtoReg, ExtOp, ALUctr, Branch, Jump} = controls;

always @(*)
case(op)
	6'b000000:    //R
		begin
			case(func)
				6'b100001: controls <= 14'b11000000000000;//addu
				6'b100011: controls <= 14'b11000000000100;//subu
				6'b101010: controls <= 14'b11000000001000;//slt
				6'b100100: controls <= 14'b11000000001100;//and
				6'b100111: controls <= 14'b11000000010000;//nor
				6'b100101: controls <= 14'b11000000010100;//or
				6'b100110: controls <= 14'b11000000011000;//xor
				6'b000000: controls <= 14'b11000000011100;//sll
				6'b000010: controls <= 14'b11000000100000;//srl
				6'b101011: controls <= 14'b11000000100100;//sltu
				6'b001001: controls <= 14'b11000000000000;//jalr
				6'b001000: controls <= 14'b10000000000000;//jr
				6'b000100: controls <= 14'b11000000110000;//sllv
				6'b000011: controls <= 14'b11000000110100;//sra
				6'b000111: controls <= 14'b11000000111000;//srav
				6'b000110: controls <= 14'b11000000111100;//srlv
			endcase
		end
	6'b001001: controls <= 14'b01100011000000;//addiu
	6'b000100: controls <= 14'b00000000000110;//beq
	6'b000101: controls <= 14'b00000000000110;//bne
	6'b100011: controls <= 14'b01101011000000;//lw
	6'b101011: controls <= 14'b00110011000000;//sw
	6'b001111: controls <= 14'b01100100000000;//lui
	6'b001010: controls <= 14'b01100011000100;//slti
	6'b001011: controls <= 14'b01100011001000;//sltiu
	6'b000001: controls <= 14'b00000000000010;//bgez,bltz 
		
	6'b000111: controls <= 14'b00000000000010;//bgtz
	6'b000110: controls <= 14'b00000000000010;//blez
	6'b100000: controls <= 14'b01101011000000;//lb
	6'b100100: controls <= 14'b01101011000000;//lbu
	6'b101000: controls <= 14'b00110011000000;//sb
	6'b001100: controls <= 14'b01100001001100;//andi
	6'b001101: controls <= 14'b01100001010000;//ori
	6'b001110: controls <= 14'b01100001010100;//xori

	
	6'b000010: controls <= 14'b00000000000001;//j
	6'b000011: controls <= 14'b01000000000001;//jal

	default: controls <= 14'b00000000000000;
endcase
endmodule

36单周期/mips.v
`include"ctrl.v"
`include"datapath.v"

module mips(clk, rst);

input clk;
input rst;

wire[5:0] 	op;
wire[4:0]	rs,rt,rd,shamt;
wire[5:0]	func;
wire		RegDst;
wire		RegWr;
wire		ALUSrc;
wire		MemWr;
wire		MemtoReg;
wire[1:0]	ExtOp;
wire[4:0]	ALUctr;
wire		Branch;
wire		Jump;	
wire[31:0]	instruction;

assign 		op = instruction[31:26];
assign 		func = instruction[5:0];
assign		rs = instruction[25:21];
assign		rt = instruction[20:16];
assign		rd = instruction[15:11];
assign		shamt = instruction[10:6];

ctrl CTRL(op, func, RegDst, RegWr, ALUSrc, MemWr, MemtoReg, ExtOp, ALUctr, Branch, Jump);
datapath DPU(RegDst, RegWr, ALUSrc, MemWr, MemtoReg, ExtOp, ALUctr, Branch, Jump, clk, rst, instruction);

endmodule

36单周期/testbench.v
`include"mips.v"

module union_ts();

reg clk;
reg rst;

integer i;
integer clk_num = 1;
integer out;

mips MIPS(clk,rst);

initial
begin
	$dumpfile("single_cpu_wave.vcd");
	$dumpvars(0, union_ts);
end

initial
begin
	forever #5 clk=~clk;
end

initial
begin
	clk <= 1;
	rst <= 0;
	#5 rst <= 1;
	#5 rst <= 0;
	//上面四行是在一个周期内进行初始化和复位 接下来才是正式开始跑CPU

	#490 $finish;
end

always @(posedge clk)
begin
	out = $fopen("out.txt", "a+");

	$fdisplay(out, "clock [%d pos]", clk_num);
	clk_num = clk_num + 1;
	$fdisplay(out, "instruction = %h", MIPS.DPU.instruction);
	$fdisplay(out, "PC = %h", {MIPS.DPU.PC, 2'b00});
	$fdisplay(out, "Registers:");
	for (i = 0; i < 32; i = i + 1)
	begin
		$fdisplay(out, "R[%d] = %h", i, MIPS.DPU.RM.rgs[i]);
	end
	$fdisplay(out, "DataMem:");
	$fdisplay(out, "DM[0000_0014H] = %h", {MIPS.DPU.DMM.dm[32'd20 + 3], MIPS.DPU.DMM.dm[32'd20 + 2], MIPS.DPU.DMM.dm[32'd20 + 1], MIPS.DPU.DMM.dm[32'd20]});
	$fdisplay(out, "DM[0000_0015H] = %h", {MIPS.DPU.DMM.dm[32'd21 + 3], MIPS.DPU.DMM.dm[32'd21 + 2], MIPS.DPU.DMM.dm[32'd21 + 1], MIPS.DPU.DMM.dm[32'd21]});
	$fdisplay(out, "DM[0000_001CH] = %h", {MIPS.DPU.DMM.dm[32'd28 + 3], MIPS.DPU.DMM.dm[32'd28 + 2], MIPS.DPU.DMM.dm[32'd28 + 1], MIPS.DPU.DMM.dm[32'd28]});
	$fdisplay(out, "-------------------------------");

	$fclose(out);
end


endmodule

36单周期/single_cpu_wave.vcd
$date
	Sat Jul  1 17:57:01 2023
$end
$version
	Icarus Verilog
$end
$timescale
	1s
$end
$scope module union_ts $end
$var reg 1 ! clk $end
$var reg 1 " rst $end
$var integer 32 # clk_num [31:0] $end
$var integer 32 $ i [31:0] $end
$var integer 32 % out [31:0] $end
$scope module MIPS $end
$var wire 1 ! clk $end
$var wire 1 " rst $end
$var wire 5 & shamt [4:0] $end
$var wire 5 ' rt [4:0] $end
$var wire 5 ( rs [4:0] $end
$var wire 5 ) rd [4:0] $end
$var wire 6 * op [5:0] $end
$var wire 32 + instruction [31:0] $end
$var wire 6 , func [5:0] $end
$var wire 1 - RegWr $end
$var wire 1 . RegDst $end
$var wire 1 / MemtoReg $end
$var wire 1 0 MemWr $end
$var wire 1 1 Jump $end
$var wire 2 2 ExtOp [1:0] $end
$var wire 1 3 Branch $end
$var wire 5 4 ALUctr [4:0] $end
$var wire 1 5 ALUSrc $end
$scope module CTRL $end
$var wire 6 6 func [5:0] $end
$var wire 6 7 op [5:0] $end
$var wire 1 - RegWr $end
$var wire 1 . RegDst $end
$var wire 1 / MemtoReg $end
$var wire 1 0 MemWr $end
$var wire 1 1 Jump $end
$var wire 2 8 ExtOp [1:0] $end
$var wire 1 3 Branch $end
$var wire 5 9 ALUctr [4:0] $end
$var wire 1 5 ALUSrc $end
$var reg 14 : controls [13:0] $end
$upscope $end
$scope module DPU $end
$var wire 1 5 ALUSrc $end
$var wire 5 ; ALUctr [4:0] $end
$var wire 1 3 Branch $end
$var wire 2 < ExtOp [1:0] $end
$var wire 1 1 Jump $end
$var wire 1 0 MemWr $end
$var wire 1 / MemtoReg $end
$var wire 1 . RegDst $end
$var wire 1 - RegWr $end
$var wire 1 ! clk $end
$var wire 1 " reset $end
$var wire 1 = zero $end
$var wire 32 > wdata [31:0] $end
$var wire 32 ? r2 [31:0] $end
$var wire 32 @ r1 [31:0] $end
$var wire 32 A instruction [31:0] $end
$var wire 32 B exout [31:0] $end
$var wire 32 C dout [31:0] $end
$var wire 32 D data2 [31:0] $end
$var wire 32 E alure [31:0] $end
$var wire 30 F PC [31:2] $end
$var wire 30 G NPC [31:2] $end
$scope module AM $end
$var wire 5 H ALUctr [4:0] $end
$var wire 5 I shamt [4:0] $end
$var wire 1 = zero $end
$var wire 32 J B [31:0] $end
$var wire 32 K A [31:0] $end
$var reg 32 L result [31:0] $end
$upscope $end
$scope module DMM $end
$var wire 1 0 MemWr $end
$var wire 32 M addr [31:0] $end
$var wire 1 ! clk $end
$var wire 6 N op [5:0] $end
$var wire 32 O dout [31:0] $end
$var wire 32 P din [31:0] $end
$upscope $end
$scope module RM $end
$var wire 1 . RegDst $end
$var wire 1 - RegWr $end
$var wire 1 ! clk $end
$var wire 6 Q func [5:0] $end
$var wire 6 R op [5:0] $end
$var wire 5 S rd [4:0] $end
$var wire 1 " reset $end
$var wire 5 T rs [4:0] $end
$var wire 5 U rt [4:0] $end
$var wire 5 V shamt [4:0] $end
$var wire 32 W rb [31:0] $end
$var wire 32 X ra [31:0] $end
$var wire 32 Y data [31:0] $end
$var wire 30 Z PC [31:2] $end
$var integer 32 [ i [31:0] $end
$upscope $end
$scope module ReOrM $end
$var wire 32 \ dout [31:0] $end
$var wire 30 ] addr [31:2] $end
$upscope $end
$scope module extM $end
$var wire 2 ^ Extop [1:0] $end
$var wire 16 _ imm16 [15:0] $end
$var reg 32 ` Exout [31:0] $end
$upscope $end
$scope module mux2_32M $end
$var wire 32 a a [31:0] $end
$var wire 32 b b [31:0] $end
$var wire 1 5 s $end
$var reg 32 c y [31:0] $end
$upscope $end
$scope module mux2_M $end
$var wire 32 d a [31:0] $end
$var wire 32 e b [31:0] $end
$var wire 1 / s $end
$var reg 32 f y [31:0] $end
$upscope $end
$scope module npc $end
$var wire 1 3 branch $end
$var wire 32 g busA [31:0] $end
$var wire 6 h func [5:0] $end
$var wire 16 i imm16 [15:0] $end
$var wire 1 1 jump $end
$var wire 6 j op [5:0] $end
$var wire 5 k rd [4:0] $end
$var wire 5 l rs [4:0] $end
$var wire 5 m rt [4:0] $end
$var wire 5 n shamt [4:0] $end
$var wire 26 o target [25:0] $end
$var wire 1 = zero $end
$var wire 30 p PC [31:2] $end
$var wire 30 q N_NPC [31:2] $end
$var wire 30 r J_NPC [31:2] $end
$var wire 30 s B_NPC [31:2] $end
$var reg 30 t NPC [31:2] $end
$upscope $end
$scope module pc $end
$var wire 30 u NPC [31:2] $end
$var wire 1 ! clk $end
$var wire 1 " reset $end
$var reg 30 v PC [31:2] $end
$upscope $end
$upscope $end
$upscope $end
$upscope $end
$enddefinitions $end
#0
$dumpvars
b0 v
b1 u
b1 t
b1 s
b10000000000000001 r
b1 q
b0 p
b10000000000000001 o
b0 n
b1 m
b0 l
b0 k
b1001 j
b1 i
b1 h
b0 g
b1 f
bx e
b1 d
b1 c
b1 b
bx a
b1 `
b1 _
b1 ^
b0 ]
b100100000000010000000000000001 \
bx [
b0 Z
b1 Y
b0 X
bx W
b0 V
b1 U
b0 T
b0 S
b1001 R
b1 Q
bx P
bx O
b1001 N
b1 M
b1 L
b0 K
b1 J
b0 I
b10000 H
b1 G
b0 F
b1 E
b1 D
bx C
b1 B
b100100000000010000000000000001 A
b0 @
bx ?
b1 >
0=
b1 <
b10000 ;
b1100011000000 :
b10000 9
b1 8
b1001 7
b1 6
15
b10000 4
03
b1 2
01
00
0/
0.
1-
b1 ,
b100100000000010000000000000001 +
b1001 *
b0 )
b0 (
b1 '
b0 &
b10000000000000000000000000000011 %
b100000 $
b10 #
0"
1!
$end
#5
0.
15
b1 2
b1 8
b1 <
b1 ^
b10000 4
b10000 9
b10000 ;
b10000 H
b1 B
b1 `
b1 b
b1100011000000 :
b1 G
b1 t
b1 u
b1001 N
b0 I
b1 _
b1 Q
b0 V
b0 S
b1001 R
b1 h
b0 n
b0 k
b10000000000000001 r
b10000000000000001 o
b1 i
b1001 j
b0 &
b0 )
b1 ,
b1 6
b1001 *
b1001 7
b1 ?
b1 P
b1 W
b1 a
b100000 [
b1 q
b1 s
b100100000000010000000000000001 +
b100100000000010000000000000001 A
b100100000000010000000000000001 \
b0 F
b0 Z
b0 ]
b0 p
b0 v
1"
0!
#10
0"
b100000 $
b11 #
1!
#15
b10000 >
b10000 Y
b10000 f
b10000 E
b10000 L
b10000 M
b10000 d
1.
05
b0 2
b0 8
b0 <
b0 ^
b111 4
b111 9
b111 ;
b111 H
b1000100000000 B
b1000100000000 `
b1000100000000 b
b11000000011100 :
b10 G
b10 t
b10 u
b0 N
b100 I
b1000100000000 _
b0 Q
b100 V
b10 S
b0 R
b0 h
b100 n
b10 k
b10001000100000000 r
b10001000100000000 o
b1000100000000 i
b0 j
b100 &
b10 )
b0 ,
b0 6
b0 *
b0 7
b10 q
b1000100000001 s
b10001000100000000 +
b10001000100000000 A
b10001000100000000 \
b1 F
b1 Z
b1 ]
b1 p
b1 v
0!
#20
b100000 $
b100 #
1!
#25
b10001 >
b10001 Y
b10001 f
b0 4
b0 9
b0 ;
b0 H
b10001 E
b10001 L
b10001 M
b10001 d
b1100000100001 B
b1100000100001 `
b1100000100001 b
b11000000000000 :
b10000 @
b10000 K
b10000 X
b10000 g
b11 G
b11 t
b11 u
b0 I
b1100000100001 _
b100001 Q
b0 V
b11 S
b10 T
b100001 h
b0 n
b11 k
b10 l
b10000010001100000100001 r
b10000010001100000100001 o
b1100000100001 i
b0 &
b11 )
b10 (
b100001 ,
b100001 6
b11 q
b1100000100011 s
b10000010001100000100001 +
b10000010001100000100001 A
b10000010001100000100001 \
b10 F
b10 Z
b10 ]
b10 p
b10 v
0!
#30
b100000 $
b101 #
1!
#35
b100 >
b100 Y
b100 f
b1000 4
b1000 9
b1000 ;
b1000 H
b10000 D
b10000 J
b10000 c
b100 E
b100 L
b100 M
b100 d
b10000010000010 B
b10000010000010 `
b10000010000010 b
b11000000100000 :
b10000 ?
b10000 P
b10000 W
b10000 a
b0 @
b0 K
b0 X
b0 g
b100 G
b100 t
b100 u
b10 I
b10000010000010 _
b10 Q
b10 V
b100 S
b10 U
b0 T
b10 h
b10 n
b100 k
b10 m
b0 l
b100010000010000010 r
b100010000010000010 o
b10000010000010 i
b10 &
b100 )
b10 '
b0 (
b10 ,
b10 6
b100 q
b10000010000101 s
b100010000010000010 +
b100010000010000010 A
b100010000010000010 \
b11 F
b11 Z
b11 ]
b11 p
b11 v
0!
#40
b100000 $
b110 #
1!
#45
0=
b1 >
b1 Y
b1 f
0.
15
b1 2
b1 8
b1 <
b1 ^
b10001 4
b10001 9
b10001 ;
b10001 H
b101 D
b101 J
b101 c
b1 E
b1 L
b1 M
b1 d
b101 B
b101 `
b101 b
b1100011000100 :
b0 ?
b0 P
b0 W
b0 a
b100 @
b100 K
b100 X
b100 g
b101 G
b101 t
b101 u
b1010 N
b0 I
b101 _
b101 Q
b0 V
b0 S
b11001 U
b100 T
b1010 R
b101 h
b0 n
b0 k
b11001 m
b100 l
b100110010000000000000101 r
b100110010000000000000101 o
b101 i
b1010 j
b0 &
b0 )
b11001 '
b100 (
b101 ,
b101 6
b1010 *
b1010 7
b101 q
b1001 s
b101000100110010000000000000101 +
b101000100110010000000000000101 A
b101000100110010000000000000101 \
b100 F
b100 Z
b100 ]
b100 p
b100 v
0!
#50
b100000 $
b111 #
1!
#55
b10 >
b10 Y
b10 f
b10 E
b10 L
b10 M
b10 d
b1 D
b1 J
b1 c
0-
05
b0 2
b0 8
b0 <
b0 ^
b0 4
b0 9
b0 ;
b0 H
13
b10000 B
b10000 `
b10000 b
b10 :
b1 @
b1 K
b1 X
b1 g
b10101 G
b10101 t
b10101 u
b1 N
b10000 _
b10000 Q
b1 U
b11001 T
b1 R
b10000 h
b1 m
b11001 l
b11001000010000000000010000 r
b11001000010000000000010000 o
b10000 i
b1 j
b1 '
b11001 (
b10000 ,
b10000 6
b1 *
b1 7
b1 ?
b1 P
b1 W
b1 a
b110 q
b10101 s
b111001000010000000000010000 +
b111001000010000000000010000 A
b111001000010000000000010000 \
b101 F
b101 Z
b101 ]
b101 p
b101 v
0!
#60
b100000 $
b1000 #
1!
#65
0=
b11000000000000000000 >
b11000000000000000000 Y
b11000000000000000000 f
1-
15
b10 2
b10 8
b10 <
b10 ^
03
b11000000000000000000 D
b11000000000000000000 J
b11000000000000000000 c
b11000000000000000000 E
b11000000000000000000 L
b11000000000000000000 M
b11000000000000000000 d
b11000000000000000000 B
b11000000000000000000 `
b11000000000000000000 b
b1100100000000 :
b0 ?
b0 P
b0 W
b0 a
b0 @
b0 K
b0 X
b0 g
b10110 G
b10110 t
b10110 u
b1111 N
b1100 _
b1100 Q
b1100 U
b0 T
b1111 R
b1100 h
b1100 m
b0 l
b11000000000000001100 r
b11000000000000001100 o
b1100 i
b1111 j
b1100 '
b0 (
b1100 ,
b1100 6
b1111 *
b1111 7
b10110 q
b100001 s
b111100000011000000000000001100 +
b111100000011000000000000001100 A
b111100000011000000000000001100 \
b10101 F
b10101 Z
b10101 ]
b10101 p
b10101 v
0!
#70
b100000 $
b1001 #
1!
#75
b1100 >
b1100 Y
b1100 f
1.
05
b0 2
b0 8
b0 <
b0 ^
b1110 4
b1110 9
b1110 ;
b1110 H
b1100 E
b1100 L
b1100 M
b1100 d
b1101000000000111 B
b1101000000000111 `
b1101000000000111 b
b11000000111000 :
b10000 @
b10000 K
b10000 X
b10000 g
b10111 G
b10111 t
b10111 u
b0 N
b1101000000000111 _
b111 Q
b11010 S
b10 T
b0 R
b111 h
b11010 k
b10 l
b10011001101000000000111 r
b10011001101000000000111 o
b1101000000000111 i
b0 j
b11010 )
b10 (
b111 ,
b111 6
b0 *
b0 7
b11000000000000000000 ?
b11000000000000000000 P
b11000000000000000000 W
b11000000000000000000 a
b10111 q
b111111111111111101000000011101 s
b10011001101000000000111 +
b10011001101000000000111 A
b10011001101000000000111 \
b10110 F
b10110 Z
b10110 ]
b10110 p
b10110 v
0!
#80
b100000 $
b1010 #
1!
#85
b11000 >
b11000 Y
b11000 f
b1100 4
b1100 9
b1100 ;
b1100 H
b1100 D
b1100 J
b1100 c
b11000 E
b11000 L
b11000 M
b11000 d
b1101100000000100 B
b1101100000000100 `
b1101100000000100 b
b11000000110000 :
b1100 ?
b1100 P
b1100 W
b1100 a
b1 @
b1 K
b1 X
b1 g
b11000 G
b11000 t
b11000 u
b1101100000000100 _
b100 Q
b11011 S
b11010 U
b1 T
b100 h
b11011 k
b11010 m
b1 l
b1110101101100000000100 r
b1110101101100000000100 o
b1101100000000100 i
b11011 )
b11010 '
b1 (
b100 ,
b100 6
b11000 q
b111111111111111101100000011011 s
b1110101101100000000100 +
b1110101101100000000100 A
b1110101101100000000100 \
b10111 F
b10111 Z
b10111 ]
b10111 p
b10111 v
0!
#90
b100000 $
b1011 #
1!
#95
b11000 >
b11000 Y
b11000 f
b0 4
b0 9
b0 ;
b0 H
b0 D
b0 J
b0 c
b11000 E
b11000 L
b11000 M
b11000 d
b1111100000001001 B
b1111100000001001 `
b1111100000001001 b
b11000000000000 :
b0 ?
b0 P
b0 W
b0 a
b11000 @
b11000 K
b11000 X
b11000 g
b110 G
b110 t
b110 u
b1111100000001001 _
b1001 Q
b11111 S
b0 U
b11011 T
b1001 h
b11111 k
b0 m
b11011 l
b11011000001111100000001001 r
b11011000001111100000001001 o
b1111100000001001 i
b11111 )
b0 '
b11011 (
b1001 ,
b1001 6
b11001 q
b111111111111111111100000100001 s
b11011000001111100000001001 +
b11011000001111100000001001 A
b11011000001111100000001001 \
b11000 F
b11000 Z
b11000 ]
b11000 p
b11000 v
0!
#100
b100000 $
b1100 #
1!
#105
b1101 >
b1101 Y
b1101 f
b1 4
b1 9
b1 ;
b1 H
b100 D
b100 J
b100 c
b1101 E
b1101 L
b1101 M
b1101 d
b10100000100011 B
b10100000100011 `
b10100000100011 b
b11000000000100 :
b100 ?
b100 P
b100 W
b100 a
b10001 @
b10001 K
b10001 X
b10001 g
b111 G
b111 t
b111 u
b10100000100011 _
b100011 Q
b101 S
b100 U
b11 T
b100011 h
b101 k
b100 m
b11 l
b11001000010100000100011 r
b11001000010100000100011 o
b10100000100011 i
b101 )
b100 '
b11 (
b100011 ,
b100011 6
b111 q
b10100000101001 s
b11001000010100000100011 +
b11001000010100000100011 A
b11001000010100000100011 \
b110 F
b110 Z
b110 ]
b110 p
b110 v
0!
#110
b100000 $
b1101 #
1!
#115
b10100 >
b10100 Y
b10100 f
0.
0-
15
10
b1 2
b1 8
b1 <
b1 ^
b10000 4
b10000 9
b10000 ;
b10000 H
b10100 D
b10100 J
b10100 c
b10100 E
b10100 L
b10100 M
b10100 d
b10100 B
b10100 `
b10100 b
b110011000000 :
b1101 ?
b1101 P
b1101 W
b1101 a
b0 @
b0 K
b0 X
b0 g
b1000 G
b1000 t
b1000 u
b101011 N
b10100 _
b10100 Q
b0 S
b101 U
b0 T
b101011 R
b10100 h
b0 k
b101 m
b0 l
b1010000000000010100 r
b1010000000000010100 o
b10100 i
b101011 j
b0 )
b101 '
b0 (
b10100 ,
b10100 6
b101011 *
b101011 7
b1000 q
b11011 s
b10101100000001010000000000010100 +
b10101100000001010000000000010100 A
b10101100000001010000000000010100 \
b111 F
b111 Z
b111 ]
b111 p
b111 v
0!
